valinix/__init__.py
valinix/exceptions.py
valinix/password.py
valinix-1.0.0.dist-info/licenses/LICENSE
valinix-1.0.0.dist-info/METADATA
valinix-1.0.0.dist-info/WHEEL
valinix-1.0.0.dist-info/top_level.txt
valinix-1.0.0.dist-info/RECORD
